LICENSE
MANIFEST.in
README.md
dev_requirements.txt
requirements.txt
setup.py
bigorna/__init__.py
bigorna/cli.py
bigorna/core.py
bigorna.egg-info/PKG-INFO
bigorna.egg-info/SOURCES.txt
bigorna.egg-info/dependency_links.txt
bigorna.egg-info/entry_points.txt
bigorna.egg-info/requires.txt
bigorna.egg-info/top_level.txt
bigorna/commons/__init__.py
bigorna/commons/config.py
bigorna/commons/event_bus.py
bigorna/cron/__init__.py
bigorna/cron/base.py
bigorna/cron/parser.py
bigorna/http/__init__.py
bigorna/http/rest.py
bigorna/http/webview.py
bigorna/http/static/css/bootstrap.min.css
bigorna/http/static/css/style.css
bigorna/http/static/fonts/glyphicons-halflings-regular.eot
bigorna/http/static/fonts/glyphicons-halflings-regular.svg
bigorna/http/static/fonts/glyphicons-halflings-regular.ttf
bigorna/http/static/fonts/glyphicons-halflings-regular.woff
bigorna/http/static/fonts/glyphicons-halflings-regular.woff2
bigorna/http/static/js/bootstrap.min.js
bigorna/http/static/js/jquery.min.js
bigorna/http/static/js/scripts.js
bigorna/http/templates/index.html
bigorna/tasks/__init__.py
bigorna/tasks/base.py
bigorna/tasks/executor.py
bigorna/tasks/sched.py
bigorna/tracker/__init__.py
bigorna/tracker/base.py
bigorna/tracker/persistence.py
tests/cronner/__init__.py
tests/cronner/test_parser.py
tests/tasks/__init__.py
tests/tasks/test_executor.py
tests/tasks/test_sched.py
tests/tasks/test_task_factory.py