Metadata-Version: 1.1
Name: bigorna
Version: 1.2.0
Summary: Bigorna is a simple job manager to submit tasks.
Home-page: https://github.com/cliixtech/bigorna/
Author: Danilo Queiroz
Author-email: dq@cliix.io
License: GPLv3
Keywords: bigorna job tracker scheduler sysadmin
Platform: UNKNOWN
Classifier: Development Status :: 4 - Beta
Classifier: License :: OSI Approved :: GNU General Public License v3 or later (GPLv3+)
Classifier: Operating System :: POSIX :: Linux
Classifier: Intended Audience :: Developers
Classifier: Intended Audience :: System Administrators
Classifier: Topic :: System :: Systems Administration
Classifier: Programming Language :: Python :: 3 :: Only
